<?xml version="1.0"?>
<feedback xmlns:xsd="http://www.w3.org/2001/XMLSchema" xmlns:xsi="http://www.w3.org/2001/XMLSchema-instance">
  <version>1.0</version>
  <report_metadata>
    <org_name>Enterprise Outlook</org_name>
    <email>dmarcreport@microsoft.com</email>
    <report_id>02b7c9aba5634849aa7c36be8d8d9eb9</report_id>
    <date_range>
      <begin>1737072000</begin>
      <end>1737158400</end>
    </date_range>
  </report_metadata>
  <policy_published>
    <domain>kaltura.email</domain>
    <adkim>r</adkim>
    <aspf>r</aspf>
    <p>none</p>
    <sp>none</sp>
    <pct>100</pct>
    <fo>1</fo>
  </policy_published>
  <record>
    <row>
      <source_ip>217.72.192.73</source_ip>
      <count>1</count>
      <policy_evaluated>
        <disposition>none</disposition>
        <dkim>pass</dkim>
        <spf>pass</spf>
      </policy_evaluated>
    </row>
    <identifiers>
      <envelope_to>grow8fig.com</envelope_to>
      <envelope_from>kaltura.email</envelope_from>
      <header_from>kaltura.email</header_from>
    </identifiers>
    <auth_results>
      <dkim>
        <domain>kaltura.email</domain>
        <selector>s1-ionos</selector>
        <result>pass</result>
      </dkim>
      <spf>
        <domain>kaltura.email</domain>
        <scope>mfrom</scope>
        <result>pass</result>
      </spf>
    </auth_results>
  </record>
  <record>
    <row>
      <source_ip>217.72.192.74</source_ip>
      <count>1</count>
      <policy_evaluated>
        <disposition>none</disposition>
        <dkim>pass</dkim>
        <spf>pass</spf>
      </policy_evaluated>
    </row>
    <identifiers>
      <envelope_to>gojombone.com</envelope_to>
      <envelope_from>kaltura.email</envelope_from>
      <header_from>kaltura.email</header_from>
    </identifiers>
    <auth_results>
      <dkim>
        <domain>kaltura.email</domain>
        <selector>s1-ionos</selector>
        <result>pass</result>
      </dkim>
      <spf>
        <domain>kaltura.email</domain>
        <scope>mfrom</scope>
        <result>pass</result>
      </spf>
    </auth_results>
  </record>
  <record>
    <row>
      <source_ip>212.227.126.133</source_ip>
      <count>1</count>
      <policy_evaluated>
        <disposition>none</disposition>
        <dkim>pass</dkim>
        <spf>pass</spf>
      </policy_evaluated>
    </row>
    <identifiers>
      <envelope_to>dtailstudiocraft.com</envelope_to>
      <envelope_from>kaltura.email</envelope_from>
      <header_from>kaltura.email</header_from>
    </identifiers>
    <auth_results>
      <dkim>
        <domain>kaltura.email</domain>
        <selector>s1-ionos</selector>
        <result>pass</result>
      </dkim>
      <spf>
        <domain>kaltura.email</domain>
        <scope>mfrom</scope>
        <result>pass</result>
      </spf>
    </auth_results>
  </record>
  <record>
    <row>
      <source_ip>212.227.126.130</source_ip>
      <count>1</count>
      <policy_evaluated>
        <disposition>none</disposition>
        <dkim>pass</dkim>
        <spf>pass</spf>
      </policy_evaluated>
    </row>
    <identifiers>
      <envelope_to>jewelpickert.net</envelope_to>
      <envelope_from>kaltura.email</envelope_from>
      <header_from>kaltura.email</header_from>
    </identifiers>
    <auth_results>
      <dkim>
        <domain>kaltura.email</domain>
        <selector>s1-ionos</selector>
        <result>pass</result>
      </dkim>
      <spf>
        <domain>kaltura.email</domain>
        <scope>mfrom</scope>
        <result>pass</result>
      </spf>
    </auth_results>
  </record>
  <record>
    <row>
      <source_ip>212.227.17.24</source_ip>
      <count>1</count>
      <policy_evaluated>
        <disposition>none</disposition>
        <dkim>pass</dkim>
        <spf>pass</spf>
      </policy_evaluated>
    </row>
    <identifiers>
      <envelope_to>justlegaladvertising.com</envelope_to>
      <envelope_from>kaltura.email</envelope_from>
      <header_from>kaltura.email</header_from>
    </identifiers>
    <auth_results>
      <dkim>
        <domain>kaltura.email</domain>
        <selector>s1-ionos</selector>
        <result>pass</result>
      </dkim>
      <spf>
        <domain>kaltura.email</domain>
        <scope>mfrom</scope>
        <result>pass</result>
      </spf>
    </auth_results>
  </record>
  <record>
    <row>
      <source_ip>212.227.126.130</source_ip>
      <count>1</count>
      <policy_evaluated>
        <disposition>none</disposition>
        <dkim>pass</dkim>
        <spf>pass</spf>
      </policy_evaluated>
    </row>
    <identifiers>
      <envelope_to>agentsynergies.com</envelope_to>
      <envelope_from>kaltura.email</envelope_from>
      <header_from>kaltura.email</header_from>
    </identifiers>
    <auth_results>
      <dkim>
        <domain>kaltura.email</domain>
        <selector>s1-ionos</selector>
        <result>pass</result>
      </dkim>
      <spf>
        <domain>kaltura.email</domain>
        <scope>mfrom</scope>
        <result>pass</result>
      </spf>
    </auth_results>
  </record>
  <record>
    <row>
      <source_ip>212.227.126.130</source_ip>
      <count>1</count>
      <policy_evaluated>
        <disposition>none</disposition>
        <dkim>pass</dkim>
        <spf>pass</spf>
      </policy_evaluated>
    </row>
    <identifiers>
      <envelope_to>lgestrategicconstructionmarketing.com</envelope_to>
      <envelope_from>kaltura.email</envelope_from>
      <header_from>kaltura.email</header_from>
    </identifiers>
    <auth_results>
      <dkim>
        <domain>kaltura.email</domain>
        <selector>s1-ionos</selector>
        <result>pass</result>
      </dkim>
      <spf>
        <domain>kaltura.email</domain>
        <scope>mfrom</scope>
        <result>pass</result>
      </spf>
    </auth_results>
  </record>
  <record>
    <row>
      <source_ip>212.227.126.187</source_ip>
      <count>1</count>
      <policy_evaluated>
        <disposition>none</disposition>
        <dkim>pass</dkim>
        <spf>pass</spf>
      </policy_evaluated>
    </row>
    <identifiers>
      <envelope_to>meet-hireoverseas.com</envelope_to>
      <envelope_from>kaltura.email</envelope_from>
      <header_from>kaltura.email</header_from>
    </identifiers>
    <auth_results>
      <dkim>
        <domain>kaltura.email</domain>
        <selector>s1-ionos</selector>
        <result>pass</result>
      </dkim>
      <spf>
        <domain>kaltura.email</domain>
        <scope>mfrom</scope>
        <result>pass</result>
      </spf>
    </auth_results>
  </record>
  <record>
    <row>
      <source_ip>212.227.126.133</source_ip>
      <count>1</count>
      <policy_evaluated>
        <disposition>none</disposition>
        <dkim>pass</dkim>
        <spf>pass</spf>
      </policy_evaluated>
    </row>
    <identifiers>
      <envelope_to>grow8fig.com</envelope_to>
      <envelope_from>kaltura.email</envelope_from>
      <header_from>kaltura.email</header_from>
    </identifiers>
    <auth_results>
      <dkim>
        <domain>kaltura.email</domain>
        <selector>s1-ionos</selector>
        <result>pass</result>
      </dkim>
      <spf>
        <domain>kaltura.email</domain>
        <scope>mfrom</scope>
        <result>pass</result>
      </spf>
    </auth_results>
  </record>
  <record>
    <row>
      <source_ip>212.227.126.187</source_ip>
      <count>1</count>
      <policy_evaluated>
        <disposition>none</disposition>
        <dkim>pass</dkim>
        <spf>pass</spf>
      </policy_evaluated>
    </row>
    <identifiers>
      <envelope_to>hellowilderoffsites.com</envelope_to>
      <envelope_from>kaltura.email</envelope_from>
      <header_from>kaltura.email</header_from>
    </identifiers>
    <auth_results>
      <dkim>
        <domain>kaltura.email</domain>
        <selector>s1-ionos</selector>
        <result>pass</result>
      </dkim>
      <spf>
        <domain>kaltura.email</domain>
        <scope>mfrom</scope>
        <result>pass</result>
      </spf>
    </auth_results>
  </record>
  <record>
    <row>
      <source_ip>212.227.126.134</source_ip>
      <count>1</count>
      <policy_evaluated>
        <disposition>none</disposition>
        <dkim>pass</dkim>
        <spf>pass</spf>
      </policy_evaluated>
    </row>
    <identifiers>
      <envelope_to>capraisingsavvy.com</envelope_to>
      <envelope_from>kaltura.email</envelope_from>
      <header_from>kaltura.email</header_from>
    </identifiers>
    <auth_results>
      <dkim>
        <domain>kaltura.email</domain>
        <selector>s1-ionos</selector>
        <result>pass</result>
      </dkim>
      <spf>
        <domain>kaltura.email</domain>
        <scope>mfrom</scope>
        <result>pass</result>
      </spf>
    </auth_results>
  </record>
  <record>
    <row>
      <source_ip>212.227.17.13</source_ip>
      <count>1</count>
      <policy_evaluated>
        <disposition>none</disposition>
        <dkim>pass</dkim>
        <spf>pass</spf>
      </policy_evaluated>
    </row>
    <identifiers>
      <envelope_to>checkfg.com</envelope_to>
      <envelope_from>kaltura.email</envelope_from>
      <header_from>kaltura.email</header_from>
    </identifiers>
    <auth_results>
      <dkim>
        <domain>kaltura.email</domain>
        <selector>s1-ionos</selector>
        <result>pass</result>
      </dkim>
      <spf>
        <domain>kaltura.email</domain>
        <scope>mfrom</scope>
        <result>pass</result>
      </spf>
    </auth_results>
  </record>
  <record>
    <row>
      <source_ip>212.227.17.13</source_ip>
      <count>1</count>
      <policy_evaluated>
        <disposition>none</disposition>
        <dkim>pass</dkim>
        <spf>pass</spf>
      </policy_evaluated>
    </row>
    <identifiers>
      <envelope_to>joinjmreidtraining.co</envelope_to>
      <envelope_from>kaltura.email</envelope_from>
      <header_from>kaltura.email</header_from>
    </identifiers>
    <auth_results>
      <dkim>
        <domain>kaltura.email</domain>
        <selector>s1-ionos</selector>
        <result>pass</result>
      </dkim>
      <spf>
        <domain>kaltura.email</domain>
        <scope>mfrom</scope>
        <result>pass</result>
      </spf>
    </auth_results>
  </record>
  <record>
    <row>
      <source_ip>212.227.126.134</source_ip>
      <count>1</count>
      <policy_evaluated>
        <disposition>none</disposition>
        <dkim>pass</dkim>
        <spf>pass</spf>
      </policy_evaluated>
    </row>
    <identifiers>
      <envelope_to>diantelife.com</envelope_to>
      <envelope_from>kaltura.email</envelope_from>
      <header_from>kaltura.email</header_from>
    </identifiers>
    <auth_results>
      <dkim>
        <domain>kaltura.email</domain>
        <selector>s1-ionos</selector>
        <result>pass</result>
      </dkim>
      <spf>
        <domain>kaltura.email</domain>
        <scope>mfrom</scope>
        <result>pass</result>
      </spf>
    </auth_results>
  </record>
  <record>
    <row>
      <source_ip>212.227.126.134</source_ip>
      <count>1</count>
      <policy_evaluated>
        <disposition>none</disposition>
        <dkim>pass</dkim>
        <spf>pass</spf>
      </policy_evaluated>
    </row>
    <identifiers>
      <envelope_to>ai-nostra.com</envelope_to>
      <envelope_from>kaltura.email</envelope_from>
      <header_from>kaltura.email</header_from>
    </identifiers>
    <auth_results>
      <dkim>
        <domain>kaltura.email</domain>
        <selector>s1-ionos</selector>
        <result>pass</result>
      </dkim>
      <spf>
        <domain>kaltura.email</domain>
        <scope>mfrom</scope>
        <result>pass</result>
      </spf>
    </auth_results>
  </record>
  <record>
    <row>
      <source_ip>212.227.126.187</source_ip>
      <count>1</count>
      <policy_evaluated>
        <disposition>none</disposition>
        <dkim>pass</dkim>
        <spf>pass</spf>
      </policy_evaluated>
    </row>
    <identifiers>
      <envelope_to>convosfromdealflow.com</envelope_to>
      <envelope_from>kaltura.email</envelope_from>
      <header_from>kaltura.email</header_from>
    </identifiers>
    <auth_results>
      <dkim>
        <domain>kaltura.email</domain>
        <selector>s1-ionos</selector>
        <result>pass</result>
      </dkim>
      <spf>
        <domain>kaltura.email</domain>
        <scope>mfrom</scope>
        <result>pass</result>
      </spf>
    </auth_results>
  </record>
  <record>
    <row>
      <source_ip>212.227.126.131</source_ip>
      <count>1</count>
      <policy_evaluated>
        <disposition>none</disposition>
        <dkim>pass</dkim>
        <spf>pass</spf>
      </policy_evaluated>
    </row>
    <identifiers>
      <envelope_to>firstgenfinancials.com</envelope_to>
      <envelope_from>kaltura.email</envelope_from>
      <header_from>kaltura.email</header_from>
    </identifiers>
    <auth_results>
      <dkim>
        <domain>kaltura.email</domain>
        <selector>s1-ionos</selector>
        <result>pass</result>
      </dkim>
      <spf>
        <domain>kaltura.email</domain>
        <scope>mfrom</scope>
        <result>pass</result>
      </spf>
    </auth_results>
  </record>
  <record>
    <row>
      <source_ip>217.72.192.74</source_ip>
      <count>1</count>
      <policy_evaluated>
        <disposition>none</disposition>
        <dkim>pass</dkim>
        <spf>pass</spf>
      </policy_evaluated>
    </row>
    <identifiers>
      <envelope_to>meridian-group-opportunities.com</envelope_to>
      <envelope_from>kaltura.email</envelope_from>
      <header_from>kaltura.email</header_from>
    </identifiers>
    <auth_results>
      <dkim>
        <domain>kaltura.email</domain>
        <selector>s1-ionos</selector>
        <result>pass</result>
      </dkim>
      <spf>
        <domain>kaltura.email</domain>
        <scope>mfrom</scope>
        <result>pass</result>
      </spf>
    </auth_results>
  </record>
  <record>
    <row>
      <source_ip>212.227.126.135</source_ip>
      <count>1</count>
      <policy_evaluated>
        <disposition>none</disposition>
        <dkim>pass</dkim>
        <spf>pass</spf>
      </policy_evaluated>
    </row>
    <identifiers>
      <envelope_to>equitybuildermystorybiobook.com</envelope_to>
      <envelope_from>kaltura.email</envelope_from>
      <header_from>kaltura.email</header_from>
    </identifiers>
    <auth_results>
      <dkim>
        <domain>kaltura.email</domain>
        <selector>s1-ionos</selector>
        <result>pass</result>
      </dkim>
      <spf>
        <domain>kaltura.email</domain>
        <scope>mfrom</scope>
        <result>pass</result>
      </spf>
    </auth_results>
  </record>
  <record>
    <row>
      <source_ip>217.72.192.74</source_ip>
      <count>1</count>
      <policy_evaluated>
        <disposition>none</disposition>
        <dkim>pass</dkim>
        <spf>pass</spf>
      </policy_evaluated>
    </row>
    <identifiers>
      <envelope_to>hyperscaleprospecting.com</envelope_to>
      <envelope_from>kaltura.email</envelope_from>
      <header_from>kaltura.email</header_from>
    </identifiers>
    <auth_results>
      <dkim>
        <domain>kaltura.email</domain>
        <selector>s1-ionos</selector>
        <result>pass</result>
      </dkim>
      <spf>
        <domain>kaltura.email</domain>
        <scope>mfrom</scope>
        <result>pass</result>
      </spf>
    </auth_results>
  </record>
  <record>
    <row>
      <source_ip>217.72.192.75</source_ip>
      <count>1</count>
      <policy_evaluated>
        <disposition>none</disposition>
        <dkim>pass</dkim>
        <spf>pass</spf>
      </policy_evaluated>
    </row>
    <identifiers>
      <envelope_to>ooodlesmodels.com</envelope_to>
      <envelope_from>kaltura.email</envelope_from>
      <header_from>kaltura.email</header_from>
    </identifiers>
    <auth_results>
      <dkim>
        <domain>kaltura.email</domain>
        <selector>s1-ionos</selector>
        <result>pass</result>
      </dkim>
      <spf>
        <domain>kaltura.email</domain>
        <scope>mfrom</scope>
        <result>pass</result>
      </spf>
    </auth_results>
  </record>
  <record>
    <row>
      <source_ip>217.72.192.73</source_ip>
      <count>1</count>
      <policy_evaluated>
        <disposition>none</disposition>
        <dkim>pass</dkim>
        <spf>pass</spf>
      </policy_evaluated>
    </row>
    <identifiers>
      <envelope_to>swishcapitalkey.com</envelope_to>
      <envelope_from>kaltura.email</envelope_from>
      <header_from>kaltura.email</header_from>
    </identifiers>
    <auth_results>
      <dkim>
        <domain>kaltura.email</domain>
        <selector>s1-ionos</selector>
        <result>pass</result>
      </dkim>
      <spf>
        <domain>kaltura.email</domain>
        <scope>mfrom</scope>
        <result>pass</result>
      </spf>
    </auth_results>
  </record>
  <record>
    <row>
      <source_ip>212.227.17.24</source_ip>
      <count>1</count>
      <policy_evaluated>
        <disposition>none</disposition>
        <dkim>pass</dkim>
        <spf>pass</spf>
      </policy_evaluated>
    </row>
    <identifiers>
      <envelope_to>planningmystorybiobook.com</envelope_to>
      <envelope_from>kaltura.email</envelope_from>
      <header_from>kaltura.email</header_from>
    </identifiers>
    <auth_results>
      <dkim>
        <domain>kaltura.email</domain>
        <selector>s1-ionos</selector>
        <result>pass</result>
      </dkim>
      <spf>
        <domain>kaltura.email</domain>
        <scope>mfrom</scope>
        <result>pass</result>
      </spf>
    </auth_results>
  </record>
  <record>
    <row>
      <source_ip>212.227.17.13</source_ip>
      <count>1</count>
      <policy_evaluated>
        <disposition>none</disposition>
        <dkim>pass</dkim>
        <spf>pass</spf>
      </policy_evaluated>
    </row>
    <identifiers>
      <envelope_to>the-exec-network.com</envelope_to>
      <envelope_from>kaltura.email</envelope_from>
      <header_from>kaltura.email</header_from>
    </identifiers>
    <auth_results>
      <dkim>
        <domain>kaltura.email</domain>
        <selector>s1-ionos</selector>
        <result>pass</result>
      </dkim>
      <spf>
        <domain>kaltura.email</domain>
        <scope>mfrom</scope>
        <result>pass</result>
      </spf>
    </auth_results>
  </record>
  <record>
    <row>
      <source_ip>212.227.17.10</source_ip>
      <count>1</count>
      <policy_evaluated>
        <disposition>none</disposition>
        <dkim>pass</dkim>
        <spf>pass</spf>
      </policy_evaluated>
    </row>
    <identifiers>
      <envelope_to>achieveoutreachinsider.com</envelope_to>
      <envelope_from>kaltura.email</envelope_from>
      <header_from>kaltura.email</header_from>
    </identifiers>
    <auth_results>
      <dkim>
        <domain>kaltura.email</domain>
        <selector>s1-ionos</selector>
        <result>pass</result>
      </dkim>
      <spf>
        <domain>kaltura.email</domain>
        <scope>mfrom</scope>
        <result>pass</result>
      </spf>
    </auth_results>
  </record>
  <record>
    <row>
      <source_ip>212.227.17.13</source_ip>
      <count>1</count>
      <policy_evaluated>
        <disposition>none</disposition>
        <dkim>pass</dkim>
        <spf>pass</spf>
      </policy_evaluated>
    </row>
    <identifiers>
      <envelope_to>evlvprivatequity.com</envelope_to>
      <envelope_from>kaltura.email</envelope_from>
      <header_from>kaltura.email</header_from>
    </identifiers>
    <auth_results>
      <dkim>
        <domain>kaltura.email</domain>
        <selector>s1-ionos</selector>
        <result>pass</result>
      </dkim>
      <spf>
        <domain>kaltura.email</domain>
        <scope>mfrom</scope>
        <result>pass</result>
      </spf>
    </auth_results>
  </record>
  <record>
    <row>
      <source_ip>217.72.192.73</source_ip>
      <count>1</count>
      <policy_evaluated>
        <disposition>none</disposition>
        <dkim>pass</dkim>
        <spf>pass</spf>
      </policy_evaluated>
    </row>
    <identifiers>
      <envelope_to>swishfundingex.com</envelope_to>
      <envelope_from>kaltura.email</envelope_from>
      <header_from>kaltura.email</header_from>
    </identifiers>
    <auth_results>
      <dkim>
        <domain>kaltura.email</domain>
        <selector>s1-ionos</selector>
        <result>pass</result>
      </dkim>
      <spf>
        <domain>kaltura.email</domain>
        <scope>mfrom</scope>
        <result>pass</result>
      </spf>
    </auth_results>
  </record>
  <record>
    <row>
      <source_ip>212.227.17.10</source_ip>
      <count>1</count>
      <policy_evaluated>
        <disposition>none</disposition>
        <dkim>pass</dkim>
        <spf>pass</spf>
      </policy_evaluated>
    </row>
    <identifiers>
      <envelope_to>skyquestinsights.com</envelope_to>
      <envelope_from>kaltura.email</envelope_from>
      <header_from>kaltura.email</header_from>
    </identifiers>
    <auth_results>
      <dkim>
        <domain>kaltura.email</domain>
        <selector>s1-ionos</selector>
        <result>pass</result>
      </dkim>
      <spf>
        <domain>kaltura.email</domain>
        <scope>mfrom</scope>
        <result>pass</result>
      </spf>
    </auth_results>
  </record>
  <record>
    <row>
      <source_ip>217.72.192.73</source_ip>
      <count>1</count>
      <policy_evaluated>
        <disposition>none</disposition>
        <dkim>pass</dkim>
        <spf>pass</spf>
      </policy_evaluated>
    </row>
    <identifiers>
      <envelope_to>tubewriterscience.com</envelope_to>
      <envelope_from>kaltura.email</envelope_from>
      <header_from>kaltura.email</header_from>
    </identifiers>
    <auth_results>
      <dkim>
        <domain>kaltura.email</domain>
        <selector>s1-ionos</selector>
        <result>pass</result>
      </dkim>
      <spf>
        <domain>kaltura.email</domain>
        <scope>mfrom</scope>
        <result>pass</result>
      </spf>
    </auth_results>
  </record>
  <record>
    <row>
      <source_ip>212.227.126.135</source_ip>
      <count>1</count>
      <policy_evaluated>
        <disposition>none</disposition>
        <dkim>pass</dkim>
        <spf>pass</spf>
      </policy_evaluated>
    </row>
    <identifiers>
      <envelope_to>robust-capitalglobal.com</envelope_to>
      <envelope_from>kaltura.email</envelope_from>
      <header_from>kaltura.email</header_from>
    </identifiers>
    <auth_results>
      <dkim>
        <domain>kaltura.email</domain>
        <selector>s1-ionos</selector>
        <result>pass</result>
      </dkim>
      <spf>
        <domain>kaltura.email</domain>
        <scope>mfrom</scope>
        <result>pass</result>
      </spf>
    </auth_results>
  </record>
  <record>
    <row>
      <source_ip>212.227.126.134</source_ip>
      <count>1</count>
      <policy_evaluated>
        <disposition>none</disposition>
        <dkim>pass</dkim>
        <spf>pass</spf>
      </policy_evaluated>
    </row>
    <identifiers>
      <envelope_to>joinjmreidleaders.co</envelope_to>
      <envelope_from>kaltura.email</envelope_from>
      <header_from>kaltura.email</header_from>
    </identifiers>
    <auth_results>
      <dkim>
        <domain>kaltura.email</domain>
        <selector>s1-ionos</selector>
        <result>pass</result>
      </dkim>
      <spf>
        <domain>kaltura.email</domain>
        <scope>mfrom</scope>
        <result>pass</result>
      </spf>
    </auth_results>
  </record>
  <record>
    <row>
      <source_ip>217.72.192.74</source_ip>
      <count>1</count>
      <policy_evaluated>
        <disposition>none</disposition>
        <dkim>pass</dkim>
        <spf>pass</spf>
      </policy_evaluated>
    </row>
    <identifiers>
      <envelope_to>finproservices.info</envelope_to>
      <envelope_from>kaltura.email</envelope_from>
      <header_from>kaltura.email</header_from>
    </identifiers>
    <auth_results>
      <dkim>
        <domain>kaltura.email</domain>
        <selector>s1-ionos</selector>
        <result>pass</result>
      </dkim>
      <spf>
        <domain>kaltura.email</domain>
        <scope>mfrom</scope>
        <result>pass</result>
      </spf>
    </auth_results>
  </record>
  <record>
    <row>
      <source_ip>217.72.192.74</source_ip>
      <count>1</count>
      <policy_evaluated>
        <disposition>none</disposition>
        <dkim>pass</dkim>
        <spf>pass</spf>
      </policy_evaluated>
    </row>
    <identifiers>
      <envelope_to>azdentalexperts.com</envelope_to>
      <envelope_from>kaltura.email</envelope_from>
      <header_from>kaltura.email</header_from>
    </identifiers>
    <auth_results>
      <dkim>
        <domain>kaltura.email</domain>
        <selector>s1-ionos</selector>
        <result>pass</result>
      </dkim>
      <spf>
        <domain>kaltura.email</domain>
        <scope>mfrom</scope>
        <result>pass</result>
      </spf>
    </auth_results>
  </record>
  <record>
    <row>
      <source_ip>212.227.126.187</source_ip>
      <count>1</count>
      <policy_evaluated>
        <disposition>none</disposition>
        <dkim>pass</dkim>
        <spf>pass</spf>
      </policy_evaluated>
    </row>
    <identifiers>
      <envelope_to>getautomateddealflow.com</envelope_to>
      <envelope_from>kaltura.email</envelope_from>
      <header_from>kaltura.email</header_from>
    </identifiers>
    <auth_results>
      <dkim>
        <domain>kaltura.email</domain>
        <selector>s1-ionos</selector>
        <result>pass</result>
      </dkim>
      <spf>
        <domain>kaltura.email</domain>
        <scope>mfrom</scope>
        <result>pass</result>
      </spf>
    </auth_results>
  </record>
  <record>
    <row>
      <source_ip>212.227.126.187</source_ip>
      <count>1</count>
      <policy_evaluated>
        <disposition>none</disposition>
        <dkim>pass</dkim>
        <spf>pass</spf>
      </policy_evaluated>
    </row>
    <identifiers>
      <envelope_to>beachbumtalent.com</envelope_to>
      <envelope_from>kaltura.email</envelope_from>
      <header_from>kaltura.email</header_from>
    </identifiers>
    <auth_results>
      <dkim>
        <domain>kaltura.email</domain>
        <selector>s1-ionos</selector>
        <result>pass</result>
      </dkim>
      <spf>
        <domain>kaltura.email</domain>
        <scope>mfrom</scope>
        <result>pass</result>
      </spf>
    </auth_results>
  </record>
  <record>
    <row>
      <source_ip>212.227.17.10</source_ip>
      <count>1</count>
      <policy_evaluated>
        <disposition>none</disposition>
        <dkim>pass</dkim>
        <spf>pass</spf>
      </policy_evaluated>
    </row>
    <identifiers>
      <envelope_to>fundsinvestmentgroupmeridian.com</envelope_to>
      <envelope_from>kaltura.email</envelope_from>
      <header_from>kaltura.email</header_from>
    </identifiers>
    <auth_results>
      <dkim>
        <domain>kaltura.email</domain>
        <selector>s1-ionos</selector>
        <result>pass</result>
      </dkim>
      <spf>
        <domain>kaltura.email</domain>
        <scope>mfrom</scope>
        <result>pass</result>
      </spf>
    </auth_results>
  </record>
  <record>
    <row>
      <source_ip>212.227.17.13</source_ip>
      <count>1</count>
      <policy_evaluated>
        <disposition>none</disposition>
        <dkim>pass</dkim>
        <spf>pass</spf>
      </policy_evaluated>
    </row>
    <identifiers>
      <envelope_to>investmentnetworkpartnersmeridian.com</envelope_to>
      <envelope_from>kaltura.email</envelope_from>
      <header_from>kaltura.email</header_from>
    </identifiers>
    <auth_results>
      <dkim>
        <domain>kaltura.email</domain>
        <selector>s1-ionos</selector>
        <result>pass</result>
      </dkim>
      <spf>
        <domain>kaltura.email</domain>
        <scope>mfrom</scope>
        <result>pass</result>
      </spf>
    </auth_results>
  </record>
  <record>
    <row>
      <source_ip>212.227.126.187</source_ip>
      <count>1</count>
      <policy_evaluated>
        <disposition>none</disposition>
        <dkim>pass</dkim>
        <spf>pass</spf>
      </policy_evaluated>
    </row>
    <identifiers>
      <envelope_to>invernessmail.com</envelope_to>
      <envelope_from>kaltura.email</envelope_from>
      <header_from>kaltura.email</header_from>
    </identifiers>
    <auth_results>
      <dkim>
        <domain>kaltura.email</domain>
        <selector>s1-ionos</selector>
        <result>pass</result>
      </dkim>
      <spf>
        <domain>kaltura.email</domain>
        <scope>mfrom</scope>
        <result>pass</result>
      </spf>
    </auth_results>
  </record>
  <record>
    <row>
      <source_ip>212.227.126.135</source_ip>
      <count>1</count>
      <policy_evaluated>
        <disposition>none</disposition>
        <dkim>pass</dkim>
        <spf>pass</spf>
      </policy_evaluated>
    </row>
    <identifiers>
      <envelope_to>xn--kstenradinfo-dlb.de</envelope_to>
      <envelope_from>kaltura.email</envelope_from>
      <header_from>kaltura.email</header_from>
    </identifiers>
    <auth_results>
      <dkim>
        <domain>kaltura.email</domain>
        <selector>s1-ionos</selector>
        <result>pass</result>
      </dkim>
      <spf>
        <domain>kaltura.email</domain>
        <scope>mfrom</scope>
        <result>pass</result>
      </spf>
    </auth_results>
  </record>
  <record>
    <row>
      <source_ip>212.227.17.10</source_ip>
      <count>1</count>
      <policy_evaluated>
        <disposition>none</disposition>
        <dkim>pass</dkim>
        <spf>pass</spf>
      </policy_evaluated>
    </row>
    <identifiers>
      <envelope_to>shipjamhub.com</envelope_to>
      <envelope_from>kaltura.email</envelope_from>
      <header_from>kaltura.email</header_from>
    </identifiers>
    <auth_results>
      <dkim>
        <domain>kaltura.email</domain>
        <selector>s1-ionos</selector>
        <result>pass</result>
      </dkim>
      <spf>
        <domain>kaltura.email</domain>
        <scope>mfrom</scope>
        <result>pass</result>
      </spf>
    </auth_results>
  </record>
  <record>
    <row>
      <source_ip>217.72.192.74</source_ip>
      <count>1</count>
      <policy_evaluated>
        <disposition>none</disposition>
        <dkim>pass</dkim>
        <spf>pass</spf>
      </policy_evaluated>
    </row>
    <identifiers>
      <envelope_to>pfmmediagroup.com</envelope_to>
      <envelope_from>kaltura.email</envelope_from>
      <header_from>kaltura.email</header_from>
    </identifiers>
    <auth_results>
      <dkim>
        <domain>kaltura.email</domain>
        <selector>s1-ionos</selector>
        <result>pass</result>
      </dkim>
      <spf>
        <domain>kaltura.email</domain>
        <scope>mfrom</scope>
        <result>pass</result>
      </spf>
    </auth_results>
  </record>
  <record>
    <row>
      <source_ip>217.72.192.73</source_ip>
      <count>1</count>
      <policy_evaluated>
        <disposition>none</disposition>
        <dkim>pass</dkim>
        <spf>pass</spf>
      </policy_evaluated>
    </row>
    <identifiers>
      <envelope_to>dealflowcapitalgroup.com</envelope_to>
      <envelope_from>kaltura.email</envelope_from>
      <header_from>kaltura.email</header_from>
    </identifiers>
    <auth_results>
      <dkim>
        <domain>kaltura.email</domain>
        <selector>s1-ionos</selector>
        <result>pass</result>
      </dkim>
      <spf>
        <domain>kaltura.email</domain>
        <scope>mfrom</scope>
        <result>pass</result>
      </spf>
    </auth_results>
  </record>
  <record>
    <row>
      <source_ip>212.227.126.134</source_ip>
      <count>1</count>
      <policy_evaluated>
        <disposition>none</disposition>
        <dkim>pass</dkim>
        <spf>pass</spf>
      </policy_evaluated>
    </row>
    <identifiers>
      <envelope_to>fulfillninja360.com</envelope_to>
      <envelope_from>kaltura.email</envelope_from>
      <header_from>kaltura.email</header_from>
    </identifiers>
    <auth_results>
      <dkim>
        <domain>kaltura.email</domain>
        <selector>s1-ionos</selector>
        <result>pass</result>
      </dkim>
      <spf>
        <domain>kaltura.email</domain>
        <scope>mfrom</scope>
        <result>pass</result>
      </spf>
    </auth_results>
  </record>
  <record>
    <row>
      <source_ip>212.227.17.10</source_ip>
      <count>1</count>
      <policy_evaluated>
        <disposition>none</disposition>
        <dkim>pass</dkim>
        <spf>pass</spf>
      </policy_evaluated>
    </row>
    <identifiers>
      <envelope_to>getblitzscaled.com</envelope_to>
      <envelope_from>kaltura.email</envelope_from>
      <header_from>kaltura.email</header_from>
    </identifiers>
    <auth_results>
      <dkim>
        <domain>kaltura.email</domain>
        <selector>s1-ionos</selector>
        <result>pass</result>
      </dkim>
      <spf>
        <domain>kaltura.email</domain>
        <scope>mfrom</scope>
        <result>pass</result>
      </spf>
    </auth_results>
  </record>
  <record>
    <row>
      <source_ip>212.227.126.135</source_ip>
      <count>1</count>
      <policy_evaluated>
        <disposition>none</disposition>
        <dkim>pass</dkim>
        <spf>pass</spf>
      </policy_evaluated>
    </row>
    <identifiers>
      <envelope_to>glp1apex.com</envelope_to>
      <envelope_from>kaltura.email</envelope_from>
      <header_from>kaltura.email</header_from>
    </identifiers>
    <auth_results>
      <dkim>
        <domain>kaltura.email</domain>
        <selector>s1-ionos</selector>
        <result>pass</result>
      </dkim>
      <spf>
        <domain>kaltura.email</domain>
        <scope>mfrom</scope>
        <result>pass</result>
      </spf>
    </auth_results>
  </record>
  <record>
    <row>
      <source_ip>217.72.192.74</source_ip>
      <count>1</count>
      <policy_evaluated>
        <disposition>none</disposition>
        <dkim>pass</dkim>
        <spf>pass</spf>
      </policy_evaluated>
    </row>
    <identifiers>
      <envelope_to>dianteemail.com</envelope_to>
      <envelope_from>kaltura.email</envelope_from>
      <header_from>kaltura.email</header_from>
    </identifiers>
    <auth_results>
      <dkim>
        <domain>kaltura.email</domain>
        <selector>s1-ionos</selector>
        <result>pass</result>
      </dkim>
      <spf>
        <domain>kaltura.email</domain>
        <scope>mfrom</scope>
        <result>pass</result>
      </spf>
    </auth_results>
  </record>
  <record>
    <row>
      <source_ip>212.227.126.187</source_ip>
      <count>1</count>
      <policy_evaluated>
        <disposition>none</disposition>
        <dkim>pass</dkim>
        <spf>pass</spf>
      </policy_evaluated>
    </row>
    <identifiers>
      <envelope_to>purewavehydrogeninfo.com</envelope_to>
      <envelope_from>kaltura.email</envelope_from>
      <header_from>kaltura.email</header_from>
    </identifiers>
    <auth_results>
      <dkim>
        <domain>kaltura.email</domain>
        <selector>s1-ionos</selector>
        <result>pass</result>
      </dkim>
      <spf>
        <domain>kaltura.email</domain>
        <scope>mfrom</scope>
        <result>pass</result>
      </spf>
    </auth_results>
  </record>
  <record>
    <row>
      <source_ip>212.227.126.187</source_ip>
      <count>1</count>
      <policy_evaluated>
        <disposition>none</disposition>
        <dkim>pass</dkim>
        <spf>pass</spf>
      </policy_evaluated>
    </row>
    <identifiers>
      <envelope_to>podquickfix.com</envelope_to>
      <envelope_from>kaltura.email</envelope_from>
      <header_from>kaltura.email</header_from>
    </identifiers>
    <auth_results>
      <dkim>
        <domain>kaltura.email</domain>
        <selector>s1-ionos</selector>
        <result>pass</result>
      </dkim>
      <spf>
        <domain>kaltura.email</domain>
        <scope>mfrom</scope>
        <result>pass</result>
      </spf>
    </auth_results>
  </record>
  <record>
    <row>
      <source_ip>212.227.126.134</source_ip>
      <count>1</count>
      <policy_evaluated>
        <disposition>none</disposition>
        <dkim>pass</dkim>
        <spf>pass</spf>
      </policy_evaluated>
    </row>
    <identifiers>
      <envelope_to>learnmultilango.com</envelope_to>
      <envelope_from>kaltura.email</envelope_from>
      <header_from>kaltura.email</header_from>
    </identifiers>
    <auth_results>
      <dkim>
        <domain>kaltura.email</domain>
        <selector>s1-ionos</selector>
        <result>pass</result>
      </dkim>
      <spf>
        <domain>kaltura.email</domain>
        <scope>mfrom</scope>
        <result>pass</result>
      </spf>
    </auth_results>
  </record>
  <record>
    <row>
      <source_ip>217.72.192.74</source_ip>
      <count>1</count>
      <policy_evaluated>
        <disposition>none</disposition>
        <dkim>pass</dkim>
        <spf>pass</spf>
      </policy_evaluated>
    </row>
    <identifiers>
      <envelope_to>getgalleysolutionsai.com</envelope_to>
      <envelope_from>kaltura.email</envelope_from>
      <header_from>kaltura.email</header_from>
    </identifiers>
    <auth_results>
      <dkim>
        <domain>kaltura.email</domain>
        <selector>s1-ionos</selector>
        <result>pass</result>
      </dkim>
      <spf>
        <domain>kaltura.email</domain>
        <scope>mfrom</scope>
        <result>pass</result>
      </spf>
    </auth_results>
  </record>
  <record>
    <row>
      <source_ip>212.227.17.24</source_ip>
      <count>1</count>
      <policy_evaluated>
        <disposition>none</disposition>
        <dkim>pass</dkim>
        <spf>pass</spf>
      </policy_evaluated>
    </row>
    <identifiers>
      <envelope_to>transporteoptimomx.com</envelope_to>
      <envelope_from>kaltura.email</envelope_from>
      <header_from>kaltura.email</header_from>
    </identifiers>
    <auth_results>
      <dkim>
        <domain>kaltura.email</domain>
        <selector>s1-ionos</selector>
        <result>pass</result>
      </dkim>
      <spf>
        <domain>kaltura.email</domain>
        <scope>mfrom</scope>
        <result>pass</result>
      </spf>
    </auth_results>
  </record>
  <record>
    <row>
      <source_ip>212.227.17.24</source_ip>
      <count>1</count>
      <policy_evaluated>
        <disposition>none</disposition>
        <dkim>pass</dkim>
        <spf>pass</spf>
      </policy_evaluated>
    </row>
    <identifiers>
      <envelope_to>cordilloroad.com</envelope_to>
      <envelope_from>kaltura.email</envelope_from>
      <header_from>kaltura.email</header_from>
    </identifiers>
    <auth_results>
      <dkim>
        <domain>kaltura.email</domain>
        <selector>s1-ionos</selector>
        <result>pass</result>
      </dkim>
      <spf>
        <domain>kaltura.email</domain>
        <scope>mfrom</scope>
        <result>pass</result>
      </spf>
    </auth_results>
  </record>
  <record>
    <row>
      <source_ip>212.227.126.133</source_ip>
      <count>1</count>
      <policy_evaluated>
        <disposition>none</disposition>
        <dkim>pass</dkim>
        <spf>pass</spf>
      </policy_evaluated>
    </row>
    <identifiers>
      <envelope_to>canaryoncoceutics.com</envelope_to>
      <envelope_from>kaltura.email</envelope_from>
      <header_from>kaltura.email</header_from>
    </identifiers>
    <auth_results>
      <dkim>
        <domain>kaltura.email</domain>
        <selector>s1-ionos</selector>
        <result>pass</result>
      </dkim>
      <spf>
        <domain>kaltura.email</domain>
        <scope>mfrom</scope>
        <result>pass</result>
      </spf>
    </auth_results>
  </record>
  <record>
    <row>
      <source_ip>212.227.17.24</source_ip>
      <count>1</count>
      <policy_evaluated>
        <disposition>none</disposition>
        <dkim>pass</dkim>
        <spf>pass</spf>
      </policy_evaluated>
    </row>
    <identifiers>
      <envelope_to>iicapfund.com</envelope_to>
      <envelope_from>kaltura.email</envelope_from>
      <header_from>kaltura.email</header_from>
    </identifiers>
    <auth_results>
      <dkim>
        <domain>kaltura.email</domain>
        <selector>s1-ionos</selector>
        <result>pass</result>
      </dkim>
      <spf>
        <domain>kaltura.email</domain>
        <scope>mfrom</scope>
        <result>pass</result>
      </spf>
    </auth_results>
  </record>
  <record>
    <row>
      <source_ip>212.227.126.133</source_ip>
      <count>1</count>
      <policy_evaluated>
        <disposition>none</disposition>
        <dkim>pass</dkim>
        <spf>pass</spf>
      </policy_evaluated>
    </row>
    <identifiers>
      <envelope_to>powernetworksat.com</envelope_to>
      <envelope_from>kaltura.email</envelope_from>
      <header_from>kaltura.email</header_from>
    </identifiers>
    <auth_results>
      <dkim>
        <domain>kaltura.email</domain>
        <selector>s1-ionos</selector>
        <result>pass</result>
      </dkim>
      <spf>
        <domain>kaltura.email</domain>
        <scope>mfrom</scope>
        <result>pass</result>
      </spf>
    </auth_results>
  </record>
  <record>
    <row>
      <source_ip>212.227.17.13</source_ip>
      <count>1</count>
      <policy_evaluated>
        <disposition>none</disposition>
        <dkim>pass</dkim>
        <spf>pass</spf>
      </policy_evaluated>
    </row>
    <identifiers>
      <envelope_to>unislinkportal.com</envelope_to>
      <envelope_from>kaltura.email</envelope_from>
      <header_from>kaltura.email</header_from>
    </identifiers>
    <auth_results>
      <dkim>
        <domain>kaltura.email</domain>
        <selector>s1-ionos</selector>
        <result>pass</result>
      </dkim>
      <spf>
        <domain>kaltura.email</domain>
        <scope>mfrom</scope>
        <result>pass</result>
      </spf>
    </auth_results>
  </record>
</feedback>